sunbi/__init__.py
sunbi/企业微信.py
sunbi/数据库.py
sunbi/文件.py
sunbi/演示.py
sunbi/网络.py
sunbi/表格.py
sunbi/邮件.py
sunbi-0.1.2.dist-info/LICENSE
sunbi-0.1.2.dist-info/METADATA
sunbi-0.1.2.dist-info/WHEEL
sunbi-0.1.2.dist-info/top_level.txt
sunbi-0.1.2.dist-info/RECORD
