Metadata-Version: 2.1
Name: sunbi
Version: 0.1.2
Summary: classes in one for Sunlands
Home-page: https://github.com/iCakeu/sunbi
Author: Dan
Author-email: danzhao@163.com
License: MIT
Platform: UNKNOWN
Classifier: License :: OSI Approved :: MIT License
Classifier: Programming Language :: Python
Classifier: Programming Language :: Python :: 3
Classifier: Programming Language :: Python :: 3.6
Classifier: Programming Language :: Python :: Implementation :: CPython
Classifier: Programming Language :: Python :: Implementation :: PyPy
Requires-Python: >=3.6.0
Requires-Dist: requests
Requires-Dist: selenium
Requires-Dist: zmail
Requires-Dist: pymysql
Provides-Extra: excelforwin
Requires-Dist: pywin32 ; extra == 'excelforwin'
Provides-Extra: _
Requires-Dist: tornado ; extra == '_'
